{"ortopedi/barnnedreextr.qmd":[],"kirurgi/rektum.qmd":[],"ortopedi/allmänfraktur.qmd":[],"kirurgi/akutbuk.qmd":[],"ortopedi/barnortopedi.qmd":[],"urologi/prostata.qmd":[],"anestesi/anestesiformer.qmd":[],"ordlista.qmd":[],"urologi/akutskrotum.qmd":[],"urologi/hematuri.qmd":[],"anestesi/dödförklaring.qmd":[],"ortopedi/övreextr.qmd":[],"anastesi/luftväg.qmd":[],"anestesi/vätskebalans.qmd":[],"ortopedi/nedreextr.qmd":[],"anestesi/preopbedömning.qmd":[],"anastesi/anestesiformer.qmd":[],"anastesi/preopbedömning.qmd":[],"anestesi/chock.qmd":[],"anestesi/läkemedel.qmd":[],"urologi/uvi.qmd":[],"urologi/urostatus.qmd":[],"urologi/penis.qmd":[],"ortopedi/ortostatus.qmd":[],"urologi/tumörer.qmd":[],"urologi/njurexpans.qmd":[],"anestesi/luftväg.qmd":[],"anastesi/chock.qmd":[],"ortopedi/rygg.qmd":[],"anastesi/läkemedel.qmd":[],"urologi/stensjukdom.qmd":[],"kirurgi/bråck.qmd":[],"index.qmd":[]}
